{
  "schemaVersion": 1,
  "kind": "sdkwork.component.spec",
  "component": {
    "name": "sdkwork-web",
    "displayName": "SDKWork Web Server",
    "version": "0.1.0",
    "type": "web-backend-service",
    "root": "sdkwork-web-server",
    "domain": "platform",
    "capability": "webserver",
    "surface": "backend-service",
    "languages": ["rust", "typescript"],
    "generated": false,
    "status": "active",
    "manifests": [
      "sdkwork.app.config.json",
      "AGENTS.md",
      "specs/component.spec.json"
    ]
  },
  "canonicalSpecs": [
    { "file": "SOUL.md", "path": "../sdkwork-specs/SOUL.md", "purpose": "SDKWork execution soul." },
    { "file": "WEB_FRAMEWORK_SPEC.md", "path": "../sdkwork-specs/WEB_FRAMEWORK_SPEC.md", "purpose": "Mandatory sdkwork-web-framework integration." },
    { "file": "WEB_BACKEND_SPEC.md", "path": "../sdkwork-specs/WEB_BACKEND_SPEC.md", "purpose": "Backend route, service, and repository boundaries." },
    { "file": "DATABASE_FRAMEWORK_SPEC.md", "path": "../sdkwork-specs/DATABASE_FRAMEWORK_SPEC.md", "purpose": "Database lifecycle and SPI orchestration." },
    { "file": "API_SPEC.md", "path": "../sdkwork-specs/API_SPEC.md", "purpose": "HTTP/OpenAPI contract rules." }
  ],
  "contracts": {
    "publicExports": [
      "crates/sdkwork-webserver-api-server",
      "crates/sdkwork-routes-webserver-app-api",
      "crates/sdkwork-routes-webserver-backend-api"
    ],
    "runtimeEntrypoints": [
      {
        "id": "api-server",
        "crate": "sdkwork-webserver-api-server",
        "binary": "sdkwork-webserver-api-server"
      }
    ]
  }
}
